lab1ex1.srcs/sources_1/new/lab1ex1.v
`timescale 1ns / 1ps

//================================================================
//================================================================
//
//          --- PART 1: DESIGN SOURCES ---
//    (These modules will be synthesized and put on the FPGA)
//
//================================================================
//================================================================


//================================================================
// Module 1: clock_divider
// Description: Takes a 100MHz clock and outputs a 1Hz tick.
//================================================================
module clock_divider(
    input wire clk, // 100 MHz
    input wire reset, // active high
    output reg tick // 1-cycle pulse at 1 Hz
);
    reg [26:0] count;

    always @(posedge clk or posedge reset) begin
        if (reset) begin
            count <= 27'd0;
            tick <= 1'b0;
        end else begin
            if (count == 27'd100_000_000 - 1) begin // 100 Million
                count <= 27'd0;
                tick <= 1'b1;
            end else begin
                count <= count + 1;
                tick <= 1'b0;
            end
        end
    end
endmodule

//================================================================
// Module 2: traffic_fsm
// Description: The "brain" of the traffic light.
//              Manages states, timers, and set mode.
//================================================================
module traffic_fsm(
    input wire clk,
    input wire reset,
    input wire tick,
    input wire set_mode,
    input wire inc_A,
    input wire dec_A,
    input wire inc_B,
    input wire dec_B,
    output reg [2:0] A_light,
    output reg [2:0] B_light,
    output reg [3:0] counter_A,
    output reg [3:0] counter_B,
    output reg [3:0] green_time_A,
    output reg [3:0] green_time_B
);
    // --- Fixed Colors (to match XDC) ---
    localparam RED    = 3'b100;
    localparam YELLOW = 3'b110;
    localparam GREEN  = 3'b010;
    // ------------------------------------

    localparam S0 = 2'b00, S1 = 2'b01, S2 = 2'b10, S3 = 2'b11;
    reg [1:0] state;

    localparam Y_TIME = 4'd2; // 2-second yellow light

    // Registers for set mode
    reg inc_A_prev, dec_A_prev, inc_B_prev, dec_B_prev;
    reg [3:0] green_time_temp_A, green_time_temp_B;

    always @(posedge clk or posedge reset) begin
        if (reset) begin
            state <= S0;
            green_time_A <= 4'd3;
            green_time_temp_A <= 4'd3;
            green_time_B <= 4'd3;
            green_time_temp_B <= 4'd3;
            
            counter_A <= 4'd3; // A starts Green
            counter_B <= 4'd5; // B starts Red (A_Green_Time + Y_Time)
            
            inc_A_prev <= 1'b0;
            dec_A_prev <= 1'b0;
            inc_B_prev <= 1'b0; dec_B_prev <= 1'b0;
        end else begin
            // Store previous button state for edge detection
            inc_A_prev <= inc_A;
            dec_A_prev <= dec_A;
            inc_B_prev <= inc_B; dec_B_prev <= dec_B;
            
            if (set_mode) begin
                // --- Set Mode Logic ---
                // Control Time A
                if (inc_A && !inc_A_prev && (green_time_temp_A < 4'd15))
                    green_time_temp_A <= green_time_temp_A + 1;
                if (dec_A && !dec_A_prev && (green_time_temp_A > 4'd1))
                    green_time_temp_A <= green_time_temp_A - 1;
                // Control Time B
                if (inc_B && !inc_B_prev && (green_time_temp_B < 4'd15))
                    green_time_temp_B <= green_time_temp_B + 1;
                if (dec_B && !dec_B_prev && (green_time_temp_B > 4'd1))
                    green_time_temp_B <= green_time_temp_B - 1;
                
                // Display current settings
                counter_A <= green_time_temp_A;
                counter_B <= green_time_temp_B;

            end else begin
                // --- Running Mode ---
                
                // Apply new times when exiting set mode
                if (green_time_A != green_time_temp_A || green_time_B != green_time_temp_B) begin
                     green_time_A <= green_time_temp_A;
                     green_time_B <= green_time_temp_B;
                     state <= S0; // Reset state machine
                     counter_A <= green_time_temp_A;
                     counter_B <= green_time_temp_A + Y_TIME; // B's red time
                end

                if (tick) begin 
                    
                    // Count both counters down
                    if (counter_A > 4'd0)
                        counter_A <= counter_A - 1;
                    if (counter_B > 4'd0)
                        counter_B <= counter_B - 1;
                        
                    // State transition logic (triggers when a timer is about to hit 0)
                    if (counter_A == 4'd1 || counter_B == 4'd1) begin
                        case (state)
                            S0: begin // A=Green, B=Red. A is about to finish.
                                state <= S1;
                                counter_A <= Y_TIME; // Load A with Yellow
                               end
                            S1: begin // A=Yellow, B=Red. A is about to finish.
                                    state <= S2;
                                    counter_A <= green_time_B + Y_TIME; // Load A with Red
                                    counter_B <= green_time_B; // Load B with Green
                               end
                            S2: begin // A=Red, B=Green. B is about to finish.
                                    state <= S3;
                                    counter_B <= Y_TIME; // Load B with Yellow
                               end
                            S3: begin // A=Red, B=Yellow. B is about to finish.
                                    state <= S0;
                                    counter_B <= green_time_A + Y_TIME; // Load B with Red
                                    counter_A <= green_time_A; // Load A with Green
                               end
                        endcase
                    end
                end
            end
        end
    end

    // Combinational logic for lights
    always @(*) begin
        case (state)
            S0: begin A_light = GREEN;  B_light = RED; end
            S1: begin A_light = YELLOW; B_light = RED; end
            S2: begin A_light = RED;    B_light = GREEN; end
            S3: begin A_light = RED;    B_light = YELLOW; end
            default: begin A_light = RED; B_light = RED; end
        endcase
    end
endmodule

//================================================================
// Module 3: traffic_top (TOP-LEVEL MODULE)
// Description: Connects all modules to the FPGA's 
//              physical inputs and outputs.
//================================================================
module traffic_top(
    input wire CLK100MHZ,
    input wire [3:0] BTN,
    input wire [1:0] SW,
    output wire [2:0] A_RGB,  // LED 4
    output wire [2:0] B_RGB,  // LED 5
    output wire [3:0] SEG_A,  // 7-seg-0
    output wire [3:0] SEG_B   // 7-seg-1
);
    wire tick;
    wire reset = SW[1];        // Use SW[1] as reset
    wire set_mode = SW[0];
    
    // Map all 4 buttons to FSM inputs
    wire inc_A = BTN[0];     // BTN[0] increases Time A
    wire dec_A = BTN[1];     // BTN[1] decreases Time A
    wire inc_B = BTN[2];     // BTN[2] increases Time B
    wire dec_B = BTN[3];     // BTN[3] decreases Time B

    // Instantiate clock divider
    clock_divider u_clkdiv(.clk(CLK100MHZ), .reset(reset), .tick(tick));

    // Internal wires
    wire [2:0] A_light_w, B_light_w;
    wire [3:0] counter_A_w, counter_B_w;
    wire [3:0] green_time_A_w, green_time_B_w;

    // Instantiate FSM
    traffic_fsm u_fsm(
        .clk(CLK100MHZ), 
        .reset(reset), 
        .tick(tick), 
        .set_mode(set_mode),
        .inc_A(inc_A), .dec_A(dec_A),
        .inc_B(inc_B), .dec_B(dec_B),
        .A_light(A_light_w), .B_light(B_light_w), 
        .counter_A(counter_A_w),
        .counter_B(counter_B_w),
        .green_time_A(green_time_A_w),
        .green_time_B(green_time_B_w)
    );
    
    // Connect FSM outputs to top-level outputs
    assign A_RGB = A_light_w;
    assign B_RGB = B_light_w;

    // 7-seg-0 (SEG_A) shows the timer for LED 4 (A)
    assign SEG_A = counter_A_w;
    // 7-seg-1 (SEG_B) shows the timer for LED 5 (B)
    assign SEG_B = counter_B_w;

endmodule

//================================================================
//================================================================
//
//          --- PART 2: SIMULATION SOURCES ---
//    (This module is the testbench and will NOT be synthesized)
//
//================================================================
//================================================================

module traffic_tb;

    // Inputs
    reg clk = 0;
    reg [3:0] btn = 4'b0000;
    reg [1:0] sw = 2'b00;

    // Outputs
    wire [2:0] a_rgb;
    wire [2:0] b_rgb;
    wire [3:0] seg_a;
    wire [3:0] seg_b;

    // Instantiate the Device Under Test (DUT)
    traffic_top dut (
        .CLK100MHZ(clk),
        .BTN(btn),
        .SW(sw),
        .A_RGB(a_rgb),
        .B_RGB(b_rgb),
        .SEG_A(seg_a),
        .SEG_B(seg_b)
    );
    
    // 1. Clock Generation (100 MHz)
    always #5 clk = ~clk; // 5ns high, 5ns low = 10ns period (100 MHz)

    // 2. Main Simulation Sequence
    initial begin
        // Setup waveform dumping
        $dumpfile("traffic_tb.vcd");
        $dumpvars(0, traffic_tb);

        // Setup console monitor
        // This monitor shows the state of the FSM, the LEDs,
        // and the values on both 7-segment displays.
        $monitor("Time=%0t SW=%b BTN=%b | A_Light=%b B_Light=%b | SegA=%d (G_TimeA=%d) | SegB=%d (G_TimeB=%d) | State=%b",
                 $time, sw, btn, a_rgb, b_rgb,
                 seg_a, dut.u_fsm.green_time_A,
                 seg_b, dut.u_fsm.green_time_B,
                 dut.u_fsm.state);
        
        // ---
        // === Phase 1: Reset the System ===
        // ---
        // SW[1] is our master reset
        sw = 2'b0010; // Assert reset
        #200;         // Hold reset for 200 ns
        sw = 2'b0000; // De-assert reset
        #100;
        
        // ---
        // === Phase 2: Run with Default Times ===
        // ---
        // Let the system run with defaults (Green=3, Yellow=2)
        // Wait for 20 seconds
        #20_000_000_000;
        
        // ---
        // === Phase 3: Test "Set Mode" (SW[0]) ===
        // ---
        sw[0] = 1'b1; // Enter Set Mode
        #2_000_000_000; // Wait 2 seconds

        // ---
        // === Phase 4: Modify Time A (LED 4 / 7-seg-0) ===
        // ---
        
        // ** Test Increase for A: Default (3) -> 5 **
        // seg_a should show 4
        btn[0] = 1'b1; #100; btn[0] = 1'b0; // Press BTN[0] (inc A)
        #2_000_000_000; // Wait 2s
        
        // seg_a should show 5
        btn[0] = 1'b1; #100; btn[0] = 1'b0; // Press BTN[0] (inc A)
        #2_000_000_000; // Wait 2s

        // ** Test Decrease for A: 5 -> 4 **
        // seg_a should show 4
        btn[1] = 1'b1; #100; btn[1] = 1'b0; // Press BTN[1] (dec A)
        #2_000_000_000; // Wait 2s
        
        // ---
        // === Phase 5: Modify Time B (LED 5 / 7-seg-1) ===
        // ---

        // ** Test Increase for B: Default (3) -> 6 **
        // seg_b should show 4
        btn[2] = 1'b1; #100; btn[2] = 1'b0; // Press BTN[2] (inc B)
        #2_000_000_000; // Wait 2s
        
        // seg_b should show 5
        btn[2] = 1'b1; #100; btn[2] = 1'b0; // Press BTN[2] (inc B)
        #2_000_000_000; // Wait 2s
        
        // seg_b should show 6
        btn[2] = 1'b1; #100; btn[2] = 1'b0; // Press BTN[2] (inc B)
        #2_000_000_000; // Wait 2s

        // ** Test Decrease for B: 6 -> 5 **
        // seg_b should show 5
        btn[3] = 1'b1; #100; btn[3] = 1'b0; // Press BTN[3] (dec B)
        #2_000_000_000; // Wait 2s

        // ---
        // === Phase 6: Exit Set Mode & Run with Custom Times ===
        // ---
        sw[0] = 1'b0; // Exit Set Mode
        #2_000_000_000; // Wait 2 seconds
        
        // System now runs with Time A = 4, Time B = 5, Yellow = 2
        // Let it run for 30 seconds
        #30_000_000_000;
        
        // ---
        // === Phase 7: Test Reset During Operation ===
        // ---
        sw = 2'b0010; // Assert reset (SW[1])
        #200;
        sw = 2'b0000; // De-assert reset
        #100;
        
        // ---
        // === Phase 8: Run with Default Times Again ===
        // ---
        // System should be back to defaults (Green=3, Yellow=2)
        // Let it run for 20 seconds
        #20_000_000_000;
        
        // 7. Finish Simulation
        $finish;
    end

endmodule

lab1ex1.sim/sim_1/behav/xsim/traffic_tb.vcd
$date
   Tue Nov  4 11:38:10 2025
$end

$version
  2025.1.0
  $dumpfile ("traffic_tb.vcd") 
$end

$timescale
  1ps
$end

$scope module traffic_tb $end
$var reg 1 ! clk $end
$var reg 4 " btn [3:0] $end
$var reg 2 # sw [1:0] $end
$var wire 3 $ a_rgb [2:0] $end
$var wire 3 % b_rgb [2:0] $end
$var wire 4 & seg_a [3:0] $end
$var wire 4 ' seg_b [3:0] $end
$scope module dut $end
$var wire 1 ( CLK100MHZ $end
$var wire 4 ) BTN [3:0] $end
$var wire 2 * SW [1:0] $end
$var wire 3 $ A_RGB [2:0] $end
$var wire 3 % B_RGB [2:0] $end
$var wire 4 & SEG_A [3:0] $end
$var wire 4 ' SEG_B [3:0] $end
$var wire 1 + tick $end
$var wire 1 , reset $end
$var wire 1 - set_mode $end
$var wire 1 . inc_A $end
$var wire 1 / dec_A $end
$var wire 1 0 inc_B $end
$var wire 1 1 dec_B $end
$var wire 3 2 A_light_w [2:0] $end
$var wire 3 3 B_light_w [2:0] $end
$var wire 4 4 counter_A_w [3:0] $end
$var wire 4 5 counter_B_w [3:0] $end
$var wire 4 6 green_time_A_w [3:0] $end
$var wire 4 7 green_time_B_w [3:0] $end
$scope module u_clkdiv $end
$var wire 1 ( clk $end
$var wire 1 , reset $end
$var reg 1 8 tick $end
$var reg 27 9 count [26:0] $end
$upscope $end
$scope module u_fsm $end
$var wire 1 ( clk $end
$var wire 1 , reset $end
$var wire 1 + tick $end
$var wire 1 - set_mode $end
$var wire 1 . inc_A $end
$var wire 1 / dec_A $end
$var wire 1 0 inc_B $end
$var wire 1 1 dec_B $end
$var reg 3 : A_light [2:0] $end
$var reg 3 ; B_light [2:0] $end
$var reg 4 < counter_A [3:0] $end
$var reg 4 = counter_B [3:0] $end
$var reg 4 > green_time_A [3:0] $end
$var reg 4 ? green_time_B [3:0] $end
$var reg 2 @ state [1:0] $end
$var reg 1 A inc_A_prev $end
$var reg 1 B dec_A_prev $end
$var reg 1 C inc_B_prev $end
$var reg 1 D dec_B_prev $end
$var reg 4 E green_time_temp_A [3:0] $end
$var reg 4 F green_time_temp_B [3:0] $end
$upscope $end
$upscope $end
$upscope $end
$enddefinitions $end

#0
$dumpvars
0!
b0 "
b10 #
b10 $
b100 %
b11 &
b101 '
0(
b0 )
b10 *
0+
1,
0-
0.
0/
00
01
b10 2
b100 3
b11 4
b101 5
b11 6
b11 7
08
b0 9
b10 :
b100 ;
b11 <
b101 =
b11 >
b11 ?
b0 @
0A
0B
0C
0D
b11 E
b11 F
$end

#5000
1!
1(

#10000
0!
0(

#15000
1!
1(

#20000
0!
0(

#25000
1!
1(

#30000
0!
0(

#35000
1!
1(

#40000
0!
0(

#45000
1!
1(

#50000
0!
0(

#55000
1!
1(

#60000
0!
0(

#65000
1!
1(

#70000
0!
0(

#75000
1!
1(

#80000
0!
0(

#85000
1!
1(

#90000
0!
0(

#95000
1!
1(

#100000
0!
0(

#105000
1!
1(

#110000
0!
0(

#115000
1!
1(

#120000
0!
0(

#125000
1!
1(

#130000
0!
0(

#135000
1!
1(

#140000
0!
0(

#145000
1!
1(

#150000
0!
0(

#155000
1!
1(

#160000
0!
0(

#165000
1!
1(

#170000
0!
0(

#175000
1!
1(

#180000
0!
0(

#185000
1!
1(

#190000
0!
0(

#195000
1!
1(

#200000
0!
b0 #
0(
b0 *
0,

#205000
1!
1(
b1 9

#210000
0!
0(

#215000
1!
1(
b10 9

#220000
0!
0(

#225000
1!
1(
b11 9

#230000
0!
0(

#235000
1!
1(
b100 9

#240000
0!
0(

#245000
1!
1(
b101 9

#250000
0!
0(

#255000
1!
1(
b110 9

#260000
0!
0(

#265000
1!
1(
b111 9

#270000
0!
0(

#275000
1!
1(
b1000 9

#280000
0!
0(

#285000
1!
1(
b1001 9

#290000
0!
0(

#295000
1!
1(
b1010 9

#300000
0!
b1 #
0(
b1 *
1-

#305000
1!
b11 '
1(
b11 5
b1011 9
b11 =

#310000
0!
0(

#315000
1!
1(
b1100 9

#320000
0!
0(

#325000
1!
1(
b1101 9

#330000
0!
0(

#335000
1!
1(
b1110 9

#340000
0!
0(

#345000
1!
1(
b1111 9

#350000
0!
0(

#355000
1!
1(
b10000 9

#360000
0!
0(

#365000
1!
1(
b10001 9

#370000
0!
0(

#375000
1!
1(
b10010 9

#380000
0!
0(

#385000
1!
1(
b10011 9

#390000
0!
0(

#395000
1!
1(
b10100 9

#400000
0!
0(

#405000
1!
1(
b10101 9

#410000
0!
0(

#415000
1!
1(
b10110 9

#420000
0!
0(

#425000
1!
1(
b10111 9

#430000
0!
0(

#435000
1!
1(
b11000 9

#440000
0!
0(

#445000
1!
1(
b11001 9

#450000
0!
0(

#455000
1!
1(
b11010 9

#460000
0!
0(

#465000
1!
1(
b11011 9

#470000
0!
0(

#475000
1!
1(
b11100 9

#480000
0!
0(

#485000
1!
1(
b11101 9

#490000
0!
0(

#495000
1!
1(
b11110 9

#500000
0!
0(

#505000
1!
1(
b11111 9

#510000
0!
0(

#515000
1!
1(
b100000 9

#520000
0!
0(

#525000
1!
1(
b100001 9

#530000
0!
0(

#535000
1!
1(
b100010 9

#540000
0!
0(

#545000
1!
1(
b100011 9

#550000
0!
0(

#555000
1!
1(
b100100 9

#560000
0!
0(

#565000
1!
1(
b100101 9

#570000
0!
0(

#575000
1!
1(
b100110 9

#580000
0!
0(

#585000
1!
1(
b100111 9

#590000
0!
0(

#595000
1!
1(
b101000 9

#600000
0!
0(

#605000
1!
1(
b101001 9

#610000
0!
0(

#615000
1!
1(
b101010 9

#620000
0!
0(

#625000
1!
1(
b101011 9

#630000
0!
0(

#635000
1!
1(
b101100 9

#640000
0!
0(

#645000
1!
1(
b101101 9

#650000
0!
0(

#655000
1!
1(
b101110 9

#660000
0!
0(

#665000
1!
1(
b101111 9

#670000
0!
0(

#675000
1!
1(
b110000 9

#680000
0!
0(

#685000
1!
1(
b110001 9

#690000
0!
0(

#695000
1!
1(
b110010 9

#700000
0!
0(

#705000
1!
1(
b110011 9

#710000
0!
0(

#715000
1!
1(
b110100 9

#720000
0!
0(

#725000
1!
1(
b110101 9

#730000
0!
0(

#735000
1!
1(
b110110 9

#740000
0!
0(

#745000
1!
1(
b110111 9

#750000
0!
0(

#755000
1!
1(
b111000 9

#760000
0!
0(

#765000
1!
1(
b111001 9

#770000
0!
0(

#775000
1!
1(
b111010 9

#780000
0!
0(

#785000
1!
1(
b111011 9

#790000
0!
0(

#795000
1!
1(
b111100 9

#800000
0!
0(

#805000
1!
1(
b111101 9

#810000
0!
0(

#815000
1!
1(
b111110 9

#820000
0!
0(

#825000
1!
1(
b111111 9

#830000
0!
0(

#835000
1!
1(
b1000000 9

#840000
0!
0(

#845000
1!
1(
b1000001 9

#850000
0!
0(

#855000
1!
1(
b1000010 9

#860000
0!
0(

#865000
1!
1(
b1000011 9

#870000
0!
0(

#875000
1!
1(
b1000100 9

#880000
0!
0(

#885000
1!
1(
b1000101 9

#890000
0!
0(

#895000
1!
1(
b1000110 9

#900000
0!
0(

#905000
1!
1(
b1000111 9

#910000
0!
0(

#915000
1!
1(
b1001000 9

#920000
0!
0(

#925000
1!
1(
b1001001 9

#930000
0!
0(

#935000
1!
1(
b1001010 9

#940000
0!
0(

#945000
1!
1(
b1001011 9

#950000
0!
0(

#955000
1!
1(
b1001100 9

#960000
0!
0(

#965000
1!
1(
b1001101 9

#970000
0!
0(

#975000
1!
1(
b1001110 9

#980000
0!
0(

#985000
1!
1(
b1001111 9

#990000
0!
0(

#995000
1!
1(
b1010000 9

